guolei_py3_qunjielong/__init__.py
guolei_py3_qunjielong/library/__init__.py
guolei_py3_qunjielong/library/api.py
guolei_py3_qunjielong-2.1.1.dist-info/LICENSE
guolei_py3_qunjielong-2.1.1.dist-info/METADATA
guolei_py3_qunjielong-2.1.1.dist-info/WHEEL
guolei_py3_qunjielong-2.1.1.dist-info/top_level.txt
guolei_py3_qunjielong-2.1.1.dist-info/RECORD
